{
 "ETag": "W/\"6842c1cfaf2b0e0dfeed9a9c583fe403b8b8b98ee2fb4f7d2e2d61e54ab7530e\"",
 "Last-Modified": "Tue, 09 Jul 2024 01:58:57 GMT",
 "base": {
  "repo": {
   "name": "pytorch-lightning-feedstock"
  }
 },
 "closed_at": null,
 "created_at": "2024-07-09T01:58:49Z",
 "draft": false,
 "head": {
  "ref": "2.3.3_h21823a"
 },
 "html_url": "https://github.com/conda-forge/pytorch-lightning-feedstock/pull/161",
 "id": 1958977646,
 "labels": [],
 "mergeable": true,
 "mergeable_state": "clean",
 "merged": false,
 "merged_at": null,
 "number": 161,
 "state": "open",
 "updated_at": "2024-07-09T01:58:57Z"
}