{
 "ETag": "W/\"5afb995a84c55b744431137ea540d08ec7aafb7e98ef666f33d0f3a4f5588e87\"",
 "Last-Modified": "Tue, 06 Aug 2024 17:13:33 GMT",
 "base": {
  "repo": {
   "name": "sirius-ms-feedstock"
  }
 },
 "closed_at": null,
 "created_at": "2024-08-06T17:13:24Z",
 "draft": false,
 "head": {
  "ref": "bot-pr_arch_h488e43"
 },
 "html_url": "https://github.com/conda-forge/sirius-ms-feedstock/pull/20",
 "id": 2006497892,
 "labels": [],
 "mergeable": null,
 "mergeable_state": "unknown",
 "merged": false,
 "merged_at": null,
 "number": 20,
 "state": "open",
 "updated_at": "2024-08-06T17:13:33Z"
}