{
 "ETag": "W/\"6588568f682b27bb1778bfb99d3eb569fb4c8da224b34f7c992a9f5a2d802768\"",
 "Last-Modified": "Fri, 24 May 2024 21:01:46 GMT",
 "base": {
  "repo": {
   "name": "python-cudnn-frontend-feedstock"
  }
 },
 "closed_at": null,
 "created_at": "2024-05-24T16:26:17Z",
 "draft": true,
 "head": {
  "ref": "1.4.0_hf80b68"
 },
 "html_url": "https://github.com/conda-forge/python-cudnn-frontend-feedstock/pull/3",
 "id": 1887202066,
 "labels": [],
 "mergeable": true,
 "mergeable_state": "clean",
 "merged": false,
 "merged_at": null,
 "number": 3,
 "state": "open",
 "updated_at": "2024-05-24T21:01:46Z"
}