{
 "ETag": "W/\"da6bdbb34f8d4d0bab08468d252851b1f6d0cd139e598037c7391867c91ee0b4\"",
 "Last-Modified": "Wed, 13 Mar 2024 00:42:51 GMT",
 "base": {
  "repo": {
   "name": "snntorch-feedstock"
  }
 },
 "closed_at": null,
 "created_at": "2024-03-13T00:42:38Z",
 "draft": false,
 "head": {
  "ref": "0.8.0_he4f3a9"
 },
 "html_url": "https://github.com/conda-forge/snntorch-feedstock/pull/12",
 "id": 1769111148,
 "labels": [],
 "mergeable": true,
 "mergeable_state": "clean",
 "merged": false,
 "merged_at": null,
 "number": 12,
 "state": "open",
 "updated_at": "2024-03-13T00:42:51Z"
}