{
 "ETag": "W/\"6148b3e937fcea64708ae23239d2155299d377f8e0d649ff2e78dbef6cca37c2\"",
 "Last-Modified": "Fri, 12 Apr 2024 18:02:21 GMT",
 "base": {
  "repo": {
   "name": "kitemmodels-feedstock"
  }
 },
 "closed_at": null,
 "created_at": "2024-04-12T18:02:13Z",
 "draft": false,
 "head": {
  "ref": "6.1.0_h386a10"
 },
 "html_url": "https://github.com/conda-forge/kitemmodels-feedstock/pull/31",
 "id": 1820648050,
 "labels": [],
 "mergeable": null,
 "mergeable_state": "unknown",
 "merged": false,
 "merged_at": null,
 "number": 31,
 "state": "open",
 "updated_at": "2024-04-12T18:02:21Z"
}