{
 "ETag": "W/\"7f58dac58a986aba320edbc1cb63f6fde2136d29814fb7ec673d98f510f54fa7\"",
 "Last-Modified": "Tue, 02 Apr 2024 07:34:05 GMT",
 "base": {
  "repo": {
   "name": "keyrings.alt-feedstock"
  }
 },
 "closed_at": "2024-04-02T07:34:05Z",
 "created_at": "2024-04-02T05:38:48Z",
 "draft": false,
 "head": {
  "ref": "5.0.1_h582143"
 },
 "html_url": "https://github.com/conda-forge/keyrings.alt-feedstock/pull/26",
 "id": 1801682985,
 "labels": [
  {
   "color": "191970",
   "default": false,
   "description": "Instruct the bot to retry the PR",
   "id": 1890951413,
   "name": "bot-rerun",
   "node_id": "MDU6TGFiZWwxODkwOTUxNDEz",
   "url": "https://api.github.com/repos/conda-forge/keyrings.alt-feedstock/labels/bot-rerun"
  },
  {
   "color": "191970",
   "default": false,
   "description": "Instruct the bot to retry the PR",
   "id": 1,
   "name": "bot-rerun",
   "node_id": "hello",
   "url": "world"
  }
 ],
 "mergeable": false,
 "mergeable_state": "dirty",
 "merged": false,
 "merged_at": null,
 "number": 26,
 "state": "closed",
 "updated_at": "2024-04-02T07:34:05Z"
}