{
 "ETag": "W/\"e94935e9cbd379edbdbd3bc0b049193bf19e8d1d1a667e182977e29bc09983b8\"",
 "Last-Modified": "Fri, 09 Aug 2024 04:17:50 GMT",
 "base": {
  "repo": {
   "name": "mlflow-feedstock"
  }
 },
 "closed_at": null,
 "created_at": "2024-07-29T21:04:28Z",
 "draft": false,
 "head": {
  "ref": "2.15.0_he26603"
 },
 "html_url": "https://github.com/conda-forge/mlflow-feedstock/pull/187",
 "id": 1993100820,
 "labels": [],
 "mergeable": true,
 "mergeable_state": "unstable",
 "merged": false,
 "merged_at": null,
 "number": 187,
 "state": "open",
 "updated_at": "2024-08-09T04:17:50Z"
}