{
 "ETag": "W/\"74f3c2c35eaf5658af818e2147842bf5630e27435ad5a35fe6af9139492467b7\"",
 "Last-Modified": "Sun, 14 Jul 2024 01:07:22 GMT",
 "base": {
  "repo": {
   "name": "metocean-api-feedstock"
  }
 },
 "closed_at": null,
 "created_at": "2024-07-14T01:07:14Z",
 "draft": false,
 "head": {
  "ref": "1.1.3_ha51a69"
 },
 "html_url": "https://github.com/conda-forge/metocean-api-feedstock/pull/7",
 "id": 1968095399,
 "labels": [],
 "mergeable": true,
 "mergeable_state": "clean",
 "merged": false,
 "merged_at": null,
 "number": 7,
 "state": "open",
 "updated_at": "2024-07-14T01:07:22Z"
}