{
 "ETag": "W/\"58785b2474f3528f37d818c72cc64e86915a6326130629d0cfde413c61130668\"",
 "Last-Modified": "Wed, 26 Jun 2024 10:55:12 GMT",
 "base": {
  "repo": {
   "name": "arcticdb-feedstock"
  }
 },
 "closed_at": "2024-06-26T10:55:11Z",
 "created_at": "2024-06-21T19:56:36Z",
 "draft": false,
 "head": {
  "ref": "rebuild-azure_core_cpp1120-0-1_h5c9bc0"
 },
 "html_url": "https://github.com/conda-forge/arcticdb-feedstock/pull/230",
 "id": 1933046827,
 "labels": [
  {
   "name": "bot-rerun"
  }
 ],
 "mergeable": false,
 "mergeable_state": "dirty",
 "merged": false,
 "merged_at": null,
 "number": 230,
 "state": "closed",
 "updated_at": "2024-06-26T10:55:12Z"
}