{
 "ETag": "W/\"6597f3cf90511d0ad9c7e83ea1285aa7e6a71cd975b0a3f0fc7f6637d9a2c371\"",
 "Last-Modified": "Thu, 14 Dec 2023 02:53:13 GMT",
 "base": {
  "repo": {
   "name": "sdl2_image-feedstock"
  }
 },
 "closed_at": null,
 "created_at": "2023-12-13T20:06:36Z",
 "draft": false,
 "head": {
  "ref": "2.8.1_h6271a8"
 },
 "html_url": "https://github.com/conda-forge/sdl2_image-feedstock/pull/30",
 "id": 1643048703,
 "labels": [],
 "mergeable": true,
 "mergeable_state": "unstable",
 "merged": false,
 "merged_at": null,
 "number": 30,
 "state": "open",
 "updated_at": "2023-12-14T02:53:13Z"
}