{
 "ETag": "W/\"6a195d9438d291d6df06b37315f365a44917c51948d1a60ebbf365014d0ebff4\"",
 "Last-Modified": "Fri, 26 Apr 2024 19:35:12 GMT",
 "base": {
  "repo": {
   "name": "lmdbm-feedstock"
  }
 },
 "closed_at": null,
 "created_at": "2024-04-26T17:40:12Z",
 "draft": false,
 "head": {
  "ref": "0.0.6_h451009"
 },
 "html_url": "https://github.com/conda-forge/lmdbm-feedstock/pull/4",
 "id": 1843252405,
 "labels": [],
 "mergeable": true,
 "mergeable_state": "clean",
 "merged": false,
 "merged_at": null,
 "number": 4,
 "state": "open",
 "updated_at": "2024-04-26T19:35:12Z"
}