{
 "ETag": "W/\"e8c40d2d5589399729f050e43d3abd9c00e807b9f2149b6ca210c3f3aa6b2181\"",
 "Last-Modified": "Wed, 31 Jul 2024 13:53:57 GMT",
 "base": {
  "repo": {
   "name": "google-cloud-build-feedstock"
  }
 },
 "closed_at": "2024-07-31T13:53:57Z",
 "created_at": "2024-07-31T02:27:13Z",
 "draft": false,
 "head": {
  "ref": "this_is_not_a_branch"
 },
 "html_url": "https://github.com/conda-forge/google-cloud-build-feedstock/pull/52",
 "id": 1995443241,
 "labels": [],
 "mergeable": null,
 "mergeable_state": "unknown",
 "merged": true,
 "merged_at": "2024-07-31T13:53:57Z",
 "number": 52,
 "state": "closed",
 "updated_at": "2024-07-31T13:53:57Z"
}