{
 "ETag": "W/\"b7893cc6f5e4225624ab07730dff4e50599818478b3e815c9e910fbf7a340755\"",
 "Last-Modified": "Wed, 10 Apr 2024 13:15:22 GMT",
 "base": {
  "repo": {
   "name": "php-feedstock"
  }
 },
 "closed_at": null,
 "created_at": "2023-05-18T09:29:56Z",
 "draft": false,
 "head": {
  "ref": "rebuild-libxml2211-0-1_hc94951"
 },
 "html_url": "https://github.com/conda-forge/php-feedstock/pull/80",
 "id": 1355425443,
 "labels": [],
 "mergeable": true,
 "mergeable_state": "unstable",
 "merged": false,
 "merged_at": null,
 "number": 80,
 "state": "open",
 "updated_at": "2023-05-18T09:30:01Z"
}