{
 "ETag": "W/\"263c528c7cf9ffa048545328b574537332c54e5a29264eb1dac945467dba0a82\"",
 "Last-Modified": "Sat, 29 Jun 2024 04:27:38 GMT",
 "base": {
  "repo": {
   "name": "conda-forge-pinning-feedstock"
  }
 },
 "closed_at": null,
 "created_at": "2024-06-29T04:27:31Z",
 "draft": false,
 "head": {
  "ref": "new_pin-uhd-4.7.0-0-_hb627da"
 },
 "html_url": "https://github.com/conda-forge/conda-forge-pinning-feedstock/pull/6092",
 "id": 1945266704,
 "labels": [],
 "mergeable": true,
 "mergeable_state": "clean",
 "merged": false,
 "merged_at": null,
 "number": 6092,
 "state": "open",
 "updated_at": "2024-06-29T04:27:38Z"
}