{
 "ETag": "W/\"f048b9cfa226065e1f422c1959b0a4433635aebb8f294599f71ab70287a22592\"",
 "Last-Modified": "Mon, 01 Jul 2024 02:50:12 GMT",
 "base": {
  "repo": {
   "name": "r-lhs-feedstock"
  }
 },
 "closed_at": "2024-07-01T05:06:04Z",
 "created_at": "2024-07-01T02:50:04Z",
 "draft": false,
 "head": {
  "ref": "1.2.0_hcd9291"
 },
 "html_url": "https://github.com/conda-forge/r-lhs-feedstock/pull/25",
 "id": 1946299978,
 "labels": [
  {
   "name": "bot-rerun"
  }
 ],
 "mergeable": false,
 "mergeable_state": "dirty",
 "merged": false,
 "merged_at": null,
 "number": 25,
 "state": "closed",
 "updated_at": "2024-07-01T05:06:05Z"
}