{
 "ETag": "W/\"62a647dec645594b062754adfec1a4cc44fa84678a766467dc3e0b5db1aa0751\"",
 "Last-Modified": "Tue, 30 Jul 2024 11:22:35 GMT",
 "base": {
  "repo": {
   "name": "gstlal-inspiral-feedstock"
  }
 },
 "closed_at": "2024-07-30T11:22:31Z",
 "created_at": "2024-07-24T18:23:29Z",
 "draft": false,
 "head": {
  "ref": "this_is_not_a_branch"
 },
 "html_url": "https://github.com/conda-forge/gstlal-inspiral-feedstock/pull/23",
 "id": 1986008602,
 "labels": [
  {
   "color": "0e8a16",
   "default": false,
   "description": "Merge the PR when CI passes",
   "id": 1890940098,
   "name": "automerge",
   "node_id": "MDU6TGFiZWwxODkwOTQwMDk4",
   "url": "https://api.github.com/repos/conda-forge/gstlal-inspiral-feedstock/labels/automerge"
  }
 ],
 "mergeable": null,
 "mergeable_state": "unknown",
 "merged": true,
 "merged_at": "2024-07-30T11:22:31Z",
 "number": 23,
 "state": "closed",
 "updated_at": "2024-07-30T11:22:35Z"
}