{
 "ETag": "W/\"98c3b2b69c60cea0213bb42134e85b1311d15bffb4e44e0e4d433d9d2c010619\"",
 "Last-Modified": "Wed, 10 Jul 2024 03:41:34 GMT",
 "base": {
  "repo": {
   "name": "archinfo-feedstock"
  }
 },
 "closed_at": null,
 "created_at": "2024-07-10T03:41:26Z",
 "draft": false,
 "head": {
  "ref": "9.2.110_he22c52"
 },
 "html_url": "https://github.com/conda-forge/archinfo-feedstock/pull/45",
 "id": 1961413487,
 "labels": [],
 "mergeable": true,
 "mergeable_state": "clean",
 "merged": false,
 "merged_at": null,
 "number": 45,
 "state": "open",
 "updated_at": "2024-07-10T03:41:34Z"
}