{
 "ETag": "W/\"1f249d2159f96028c179ae668bd2185691c3057a50ea82252d3424060525b123\"",
 "Last-Modified": "Tue, 11 Jun 2024 01:50:19 GMT",
 "base": {
  "repo": {
   "name": "h2o-wave-feedstock"
  }
 },
 "closed_at": "2024-06-11T01:50:14Z",
 "created_at": "2024-06-11T01:45:03Z",
 "draft": false,
 "head": {
  "ref": "this_is_not_a_branch"
 },
 "html_url": "https://github.com/conda-forge/h2o-wave-feedstock/pull/10",
 "id": 1913358642,
 "labels": [],
 "mergeable": null,
 "mergeable_state": "unknown",
 "merged": true,
 "merged_at": "2024-06-11T01:50:14Z",
 "number": 10,
 "state": "closed",
 "updated_at": "2024-06-11T01:50:19Z"
}