{
 "ETag": "W/\"f6e18890853d94bc436bf22a7aaae3fc664a16dd2c105179f3885f4a46e8f825\"",
 "Last-Modified": "Sat, 18 May 2024 11:17:29 GMT",
 "base": {
  "repo": {
   "name": "assimulo-feedstock"
  }
 },
 "closed_at": null,
 "created_at": "2024-05-18T11:17:20Z",
 "draft": false,
 "head": {
  "ref": "rebuild-numpy2-0-1_hcfddcf"
 },
 "html_url": "https://github.com/conda-forge/assimulo-feedstock/pull/100",
 "id": 1876702466,
 "labels": [],
 "mergeable": true,
 "mergeable_state": "clean",
 "merged": false,
 "merged_at": null,
 "number": 100,
 "state": "open",
 "updated_at": "2024-05-18T11:17:29Z"
}