{
 "ETag": "W/\"ad22296565e45cb79551f4835f7bb3db948ec334d46be71173bcf65ccf224dd3\"",
 "Last-Modified": "Wed, 17 Jul 2024 13:31:45 GMT",
 "base": {
  "repo": {
   "name": "dbt-semantic-interfaces-feedstock"
  }
 },
 "closed_at": "2024-07-17T13:31:40Z",
 "created_at": "2024-07-17T13:27:01Z",
 "draft": false,
 "head": {
  "ref": "this_is_not_a_branch"
 },
 "html_url": "https://github.com/conda-forge/dbt-semantic-interfaces-feedstock/pull/27",
 "id": 1973722370,
 "labels": [],
 "mergeable": null,
 "mergeable_state": "unknown",
 "merged": true,
 "merged_at": "2024-07-17T13:31:40Z",
 "number": 27,
 "state": "closed",
 "updated_at": "2024-07-17T13:31:45Z"
}