{
 "ETag": "W/\"ad4c1eb56ef8f528be3304ec190f6ff288fe1172a199970981eb64faa04755c3\"",
 "Last-Modified": "Tue, 16 Apr 2024 14:28:10 GMT",
 "base": {
  "repo": {
   "name": "mlsauce-feedstock"
  }
 },
 "closed_at": null,
 "created_at": "2024-04-16T14:28:00Z",
 "draft": false,
 "head": {
  "ref": "0.12.2_hb47263"
 },
 "html_url": "https://github.com/conda-forge/mlsauce-feedstock/pull/4",
 "id": 1825570335,
 "labels": [],
 "mergeable": false,
 "mergeable_state": "dirty",
 "merged": false,
 "merged_at": null,
 "number": 4,
 "state": "open",
 "updated_at": "2024-04-16T14:28:10Z"
}