{
 "ETag": "W/\"da2f5f9fc5d6553c25ea0eca2d8d0602a3b993c9ca324d5e908e4d8a26e37179\"",
 "Last-Modified": "Tue, 06 Aug 2024 09:56:28 GMT",
 "base": {
  "repo": {
   "name": "conda-forge-pinning-feedstock"
  }
 },
 "closed_at": null,
 "created_at": "2024-08-06T09:56:12Z",
 "draft": false,
 "head": {
  "ref": "new_pin-aws_c_http-0.8.6-0-_h6b384d"
 },
 "html_url": "https://github.com/conda-forge/conda-forge-pinning-feedstock/pull/6249",
 "id": 2005697165,
 "labels": [],
 "mergeable": null,
 "mergeable_state": "unknown",
 "merged": false,
 "merged_at": null,
 "number": 6249,
 "state": "open",
 "updated_at": "2024-08-06T09:56:28Z"
}