{
 "ETag": "W/\"edf911955b41a2d4565045d1d57e6c4f9c6853b8e7372e97863677636f283d30\"",
 "Last-Modified": "Tue, 04 Jun 2024 05:27:16 GMT",
 "base": {
  "repo": {
   "name": "scikit-lego-feedstock"
  }
 },
 "closed_at": "2024-06-04T05:27:16Z",
 "created_at": "2024-05-27T02:02:04Z",
 "draft": false,
 "head": {
  "ref": "this_is_not_a_branch"
 },
 "html_url": "https://github.com/conda-forge/scikit-lego-feedstock/pull/28",
 "id": 1889221016,
 "labels": [],
 "mergeable": null,
 "mergeable_state": "unknown",
 "merged": true,
 "merged_at": "2024-06-04T05:27:15Z",
 "number": 28,
 "state": "closed",
 "updated_at": "2024-06-04T05:27:16Z"
}