{
 "ETag": "W/\"1ef5c2879f002b97fde91829b42a723831a8979a26af1e8221590db673a65c45\"",
 "Last-Modified": "Sun, 14 Apr 2024 22:45:04 GMT",
 "base": {
  "repo": {
   "name": "lineax-feedstock"
  }
 },
 "closed_at": null,
 "created_at": "2024-04-14T21:07:47Z",
 "draft": false,
 "head": {
  "ref": "0.0.5_hcdb5b8"
 },
 "html_url": "https://github.com/conda-forge/lineax-feedstock/pull/1",
 "id": 1822121123,
 "labels": [
  {
   "color": "0e8a16",
   "default": false,
   "description": "Merge the PR when CI passes",
   "id": 6531351384,
   "name": "automerge",
   "node_id": "LA_kwDOLPbg0s8AAAABhUyDWA",
   "url": "https://api.github.com/repos/conda-forge/lineax-feedstock/labels/automerge"
  }
 ],
 "mergeable": true,
 "mergeable_state": "unstable",
 "merged": false,
 "merged_at": null,
 "number": 1,
 "state": "open",
 "updated_at": "2024-04-14T22:45:04Z"
}