{
 "ETag": "W/\"2ba374e898571f85a2744aca23f5a5964c1d3ef271e8a300b095b8609674dbb9\"",
 "Last-Modified": "Mon, 10 Jun 2024 23:42:36 GMT",
 "base": {
  "repo": {
   "name": "typstyle-feedstock"
  }
 },
 "closed_at": null,
 "created_at": "2024-06-10T23:42:28Z",
 "draft": false,
 "head": {
  "ref": "bot-pr_arch_h801649"
 },
 "html_url": "https://github.com/conda-forge/typstyle-feedstock/pull/1",
 "id": 1913241601,
 "labels": [],
 "mergeable": true,
 "mergeable_state": "clean",
 "merged": false,
 "merged_at": null,
 "number": 1,
 "state": "open",
 "updated_at": "2024-06-10T23:42:36Z"
}