{
 "ETag": "W/\"077936451b542be5ff977bbe3c613634072f3d1abc7fe16366bb2c11e5157319\"",
 "Last-Modified": "Thu, 02 May 2024 01:38:16 GMT",
 "base": {
  "repo": {
   "name": "regional-mom6-feedstock"
  }
 },
 "closed_at": "2024-05-02T01:38:16Z",
 "created_at": "2024-04-30T18:10:34Z",
 "draft": false,
 "head": {
  "ref": "this_is_not_a_branch"
 },
 "html_url": "https://github.com/conda-forge/regional-mom6-feedstock/pull/2",
 "id": 1848510153,
 "labels": [],
 "mergeable": null,
 "mergeable_state": "unknown",
 "merged": true,
 "merged_at": "2024-05-02T01:38:16Z",
 "number": 2,
 "state": "closed",
 "updated_at": "2024-05-02T01:38:16Z"
}