{
 "ETag": "W/\"af85c3091f6f2f50707c2980285d2475855578cc03b1c86c78f0631864348f20\"",
 "Last-Modified": "Tue, 16 Jul 2024 02:55:42 GMT",
 "base": {
  "repo": {
   "name": "healpy-feedstock"
  }
 },
 "closed_at": null,
 "created_at": "2024-07-16T02:55:34Z",
 "draft": false,
 "head": {
  "ref": "1.17.3_had2347"
 },
 "html_url": "https://github.com/conda-forge/healpy-feedstock/pull/71",
 "id": 1970620314,
 "labels": [],
 "mergeable": true,
 "mergeable_state": "clean",
 "merged": false,
 "merged_at": null,
 "number": 71,
 "state": "open",
 "updated_at": "2024-07-16T02:55:42Z"
}