{
 "ETag": "W/\"32367b3c0133dcd949f7c8e80c345a585951b9ef699f01b0127754ffdcd17926\"",
 "Last-Modified": "Wed, 24 Jul 2024 21:23:30 GMT",
 "base": {
  "repo": {
   "name": "fontmath-feedstock"
  }
 },
 "closed_at": "2024-07-24T21:23:25Z",
 "created_at": "2024-07-24T21:18:16Z",
 "draft": false,
 "head": {
  "ref": "this_is_not_a_branch"
 },
 "html_url": "https://github.com/conda-forge/fontmath-feedstock/pull/4",
 "id": 1986256363,
 "labels": [],
 "mergeable": null,
 "mergeable_state": "unknown",
 "merged": true,
 "merged_at": "2024-07-24T21:23:25Z",
 "number": 4,
 "state": "closed",
 "updated_at": "2024-07-24T21:23:30Z"
}