{
 "ETag": "W/\"70638729d65567cf143f1e812a2171080e388c4cf287abb4441c875b6534b391\"",
 "Last-Modified": "Mon, 29 Apr 2024 22:34:43 GMT",
 "base": {
  "repo": {
   "name": "jupyverse-feedstock"
  }
 },
 "closed_at": null,
 "created_at": "2024-04-29T22:34:36Z",
 "draft": false,
 "head": {
  "ref": "0.5.1_h029581"
 },
 "html_url": "https://github.com/conda-forge/jupyverse-feedstock/pull/38",
 "id": 1846690459,
 "labels": [],
 "mergeable": true,
 "mergeable_state": "clean",
 "merged": false,
 "merged_at": null,
 "number": 38,
 "state": "open",
 "updated_at": "2024-04-29T22:34:43Z"
}