{
 "ETag": "W/\"2d136a76edb49a6f9c09436cb8a9c20d4046d2703bc16b111ad22dbd500906e9\"",
 "Last-Modified": "Wed, 17 Apr 2024 18:16:18 GMT",
 "base": {
  "repo": {
   "name": "conda-forge-pinning-feedstock"
  }
 },
 "closed_at": null,
 "created_at": "2024-04-17T17:06:11Z",
 "draft": false,
 "head": {
  "ref": "new_pin-poppler-24.04-0-_h6613d1"
 },
 "html_url": "https://github.com/conda-forge/conda-forge-pinning-feedstock/pull/5776",
 "id": 1827864558,
 "labels": [],
 "mergeable": true,
 "mergeable_state": "clean",
 "merged": false,
 "merged_at": null,
 "number": 5776,
 "state": "open",
 "updated_at": "2024-04-17T18:16:18Z"
}