{
 "ETag": "W/\"646227b87d4a1edf6517a1d8618faca1123c4d42e159e1bfd1e01f4ef574edb4\"",
 "Last-Modified": "Fri, 22 Mar 2024 15:14:16 GMT",
 "base": {
  "repo": {
   "name": "mpas-analysis-feedstock"
  }
 },
 "closed_at": "2024-03-22T15:12:20Z",
 "created_at": "2024-03-22T14:02:29Z",
 "draft": false,
 "head": {
  "ref": "this_is_not_a_branch"
 },
 "html_url": "https://github.com/conda-forge/mpas-analysis-feedstock/pull/51",
 "id": 1786650483,
 "labels": [
  {
   "color": "0e8a16",
   "default": false,
   "description": "Merge the PR when CI passes",
   "id": 1891020538,
   "name": "automerge",
   "node_id": "MDU6TGFiZWwxODkxMDIwNTM4",
   "url": "https://api.github.com/repos/conda-forge/mpas-analysis-feedstock/labels/automerge"
  }
 ],
 "mergeable": null,
 "mergeable_state": "unknown",
 "merged": true,
 "merged_at": "2024-03-22T15:12:20Z",
 "number": 51,
 "state": "closed",
 "updated_at": "2024-03-22T15:14:16Z"
}