{
 "ETag": "W/\"dd329423686ccad183d5f7c39faf6a99a13758ab2b5218b966226c79c138eb6b\"",
 "Last-Modified": "Wed, 20 Mar 2024 16:42:17 GMT",
 "base": {
  "repo": {
   "name": "conda-forge-pinning-feedstock"
  }
 },
 "closed_at": null,
 "created_at": "2024-03-20T16:42:08Z",
 "draft": false,
 "head": {
  "ref": "new_pin-s2n-1.4.8-0-_hdd3b07"
 },
 "html_url": "https://github.com/conda-forge/conda-forge-pinning-feedstock/pull/5656",
 "id": 1782536047,
 "labels": [],
 "mergeable": null,
 "mergeable_state": "unknown",
 "merged": false,
 "merged_at": null,
 "number": 5656,
 "state": "open",
 "updated_at": "2024-03-20T16:42:17Z"
}