{
 "ETag": "W/\"75fe85379c52ba18ef3b6657d9e19106da29c5b0645bd149bceb4417b76aa456\"",
 "Last-Modified": "Fri, 21 Jun 2024 23:04:47 GMT",
 "base": {
  "repo": {
   "name": "ray-packages-feedstock"
  }
 },
 "closed_at": null,
 "created_at": "2024-06-21T05:13:34Z",
 "draft": false,
 "head": {
  "ref": "2.30.0_h1cf474"
 },
 "html_url": "https://github.com/conda-forge/ray-packages-feedstock/pull/165",
 "id": 1931757185,
 "labels": [],
 "mergeable": true,
 "mergeable_state": "unstable",
 "merged": false,
 "merged_at": null,
 "number": 165,
 "state": "open",
 "updated_at": "2024-06-21T23:04:47Z"
}