{
 "ETag": "W/\"20952a2e36cbb0d490da3f32abc137437205c658a893dbf5dbdbfd5c9460ea0d\"",
 "Last-Modified": "Mon, 08 Jul 2024 14:07:24 GMT",
 "base": {
  "repo": {
   "name": "pdftotext-feedstock"
  }
 },
 "closed_at": "2024-07-08T14:07:24Z",
 "created_at": "2024-07-08T13:26:10Z",
 "draft": false,
 "head": {
  "ref": "this_is_not_a_branch"
 },
 "html_url": "https://github.com/conda-forge/pdftotext-feedstock/pull/38",
 "id": 1957829952,
 "labels": [],
 "mergeable": null,
 "mergeable_state": "unknown",
 "merged": true,
 "merged_at": "2024-07-08T14:07:24Z",
 "number": 38,
 "state": "closed",
 "updated_at": "2024-07-08T14:07:24Z"
}