{
 "ETag": "W/\"2b5bddeb3e670a6cb1c0d482de75bb33985cb3bc4f2566270cc61d6ffc439637\"",
 "Last-Modified": "Thu, 06 Jun 2024 04:39:42 GMT",
 "base": {
  "repo": {
   "name": "kaggle-environments-feedstock"
  }
 },
 "closed_at": null,
 "created_at": "2024-06-06T04:39:34Z",
 "draft": false,
 "head": {
  "ref": "1.14.13_h360956"
 },
 "html_url": "https://github.com/conda-forge/kaggle-environments-feedstock/pull/15",
 "id": 1906388093,
 "labels": [],
 "mergeable": true,
 "mergeable_state": "unstable",
 "merged": false,
 "merged_at": null,
 "number": 15,
 "state": "open",
 "updated_at": "2024-06-06T04:39:42Z"
}