{
 "ETag": "W/\"8c789b7586397ea5978cd5508256814a29e6920dce10cc7fb9263406b8a8b7a0\"",
 "Last-Modified": "Sun, 11 Aug 2024 23:01:38 GMT",
 "base": {
  "repo": {
   "name": "zipp-feedstock"
  }
 },
 "closed_at": null,
 "created_at": "2024-08-11T22:57:28Z",
 "draft": false,
 "head": {
  "ref": "3.20.0_h8d5be7"
 },
 "html_url": "https://github.com/conda-forge/zipp-feedstock/pull/61",
 "id": 2013988601,
 "labels": [],
 "mergeable": true,
 "mergeable_state": "unstable",
 "merged": false,
 "merged_at": null,
 "number": 61,
 "state": "open",
 "updated_at": "2024-08-11T23:01:38Z"
}