{
 "ETag": "W/\"38c8493a832821f4a4d5789a85bc9304da783849727587d60ae0fd07acb71c8a\"",
 "Last-Modified": "Thu, 02 May 2024 10:39:34 GMT",
 "base": {
  "repo": {
   "name": "deepface-feedstock"
  }
 },
 "closed_at": null,
 "created_at": "2024-05-02T10:39:27Z",
 "draft": false,
 "head": {
  "ref": "0.0.91_h0b7ac2"
 },
 "html_url": "https://github.com/conda-forge/deepface-feedstock/pull/17",
 "id": 1851207555,
 "labels": [],
 "mergeable": true,
 "mergeable_state": "unstable",
 "merged": false,
 "merged_at": null,
 "number": 17,
 "state": "open",
 "updated_at": "2024-05-02T10:39:34Z"
}