{
 "ETag": "W/\"1c38cbe3253e719d529ca756d1cdf31dcdf7c69a949877685f09ad4f4f1849b9\"",
 "Last-Modified": "Sat, 18 May 2024 02:11:08 GMT",
 "base": {
  "repo": {
   "name": "librerun-sdk-feedstock"
  }
 },
 "closed_at": "2024-05-18T02:11:07Z",
 "created_at": "2024-05-16T21:48:09Z",
 "draft": false,
 "head": {
  "ref": "this_is_not_a_branch"
 },
 "html_url": "https://github.com/conda-forge/librerun-sdk-feedstock/pull/8",
 "id": 1874365763,
 "labels": [],
 "mergeable": null,
 "mergeable_state": "unknown",
 "merged": true,
 "merged_at": "2024-05-18T02:11:07Z",
 "number": 8,
 "state": "closed",
 "updated_at": "2024-05-18T02:11:08Z"
}