{
 "ETag": "W/\"e3c8683b2195a85baaf982c3669deeebdb91f70bfac5838d0b583d6291fcbd99\"",
 "Last-Modified": "Thu, 23 May 2024 15:31:20 GMT",
 "base": {
  "repo": {
   "name": "arrow-cpp-feedstock"
  }
 },
 "closed_at": null,
 "created_at": "2024-05-23T14:48:42Z",
 "draft": false,
 "head": {
  "ref": "rebuild-aws_crt_cpp0269-0-1_h977ae6"
 },
 "html_url": "https://github.com/conda-forge/arrow-cpp-feedstock/pull/1426",
 "id": 1884792233,
 "labels": [],
 "mergeable": true,
 "mergeable_state": "clean",
 "merged": false,
 "merged_at": null,
 "number": 1426,
 "state": "open",
 "updated_at": "2024-05-23T15:31:20Z"
}