{
 "ETag": "W/\"90a2834276781062853d32d778203fc54cfa95b754d22d6c46d2b0163f7f220f\"",
 "Last-Modified": "Wed, 10 Apr 2024 13:15:22 GMT",
 "base": {
  "repo": {
   "name": "munge-feedstock"
  }
 },
 "closed_at": null,
 "created_at": "2024-03-16T01:54:00Z",
 "draft": false,
 "head": {
  "ref": "0.5.16_hdc42b3"
 },
 "html_url": "https://github.com/conda-forge/munge-feedstock/pull/7",
 "id": 1775206735,
 "labels": [],
 "mergeable": null,
 "mergeable_state": "unknown",
 "merged": false,
 "merged_at": null,
 "number": 7,
 "state": "open",
 "updated_at": "2024-03-16T01:54:08Z"
}