{
 "ETag": "W/\"90a66114b92ec1f973ec9849f5e99ec9f0d7dfc306bc9d5b64cc5c1f9bde2a1d\"",
 "Last-Modified": "Tue, 21 May 2024 02:04:30 GMT",
 "base": {
  "repo": {
   "name": "pynfft-feedstock"
  }
 },
 "closed_at": null,
 "created_at": "2024-05-21T02:04:12Z",
 "draft": false,
 "head": {
  "ref": "rebuild-numpy2-0-1_h4fd72f"
 },
 "html_url": "https://github.com/conda-forge/pynfft-feedstock/pull/20",
 "id": 1879378333,
 "labels": [],
 "mergeable": true,
 "mergeable_state": "unstable",
 "merged": false,
 "merged_at": null,
 "number": 20,
 "state": "open",
 "updated_at": "2024-05-21T02:04:30Z"
}