{
 "ETag": "W/\"15b575f72e5d9d36b15b52c76c2004ecc4395b703bc1ab5c54b591237c0baaa5\"",
 "Last-Modified": "Sun, 21 Jul 2024 00:09:42 GMT",
 "base": {
  "repo": {
   "name": "r-archive-feedstock"
  }
 },
 "closed_at": "2024-07-21T00:09:37Z",
 "created_at": "2024-07-21T00:03:26Z",
 "draft": false,
 "head": {
  "ref": "this_is_not_a_branch"
 },
 "html_url": "https://github.com/conda-forge/r-archive-feedstock/pull/7",
 "id": 1979709599,
 "labels": [],
 "mergeable": null,
 "mergeable_state": "unknown",
 "merged": true,
 "merged_at": "2024-07-21T00:09:37Z",
 "number": 7,
 "state": "closed",
 "updated_at": "2024-07-21T00:09:42Z"
}