{
 "ETag": "W/\"743281a3ac38cc9feb03d723158246297cf44c5f1d397f9992bfd8fbc0708a0f\"",
 "Last-Modified": "Thu, 27 Jun 2024 12:45:49 GMT",
 "base": {
  "repo": {
   "name": "apache-airflow-providers-databricks-feedstock"
  }
 },
 "closed_at": "2024-06-27T12:45:43Z",
 "created_at": "2024-06-27T12:18:41Z",
 "draft": false,
 "head": {
  "ref": "this_is_not_a_branch"
 },
 "html_url": "https://github.com/conda-forge/apache-airflow-providers-databricks-feedstock/pull/36",
 "id": 1942211276,
 "labels": [
  {
   "color": "0e8a16",
   "default": false,
   "description": "Merge the PR when CI passes",
   "id": 2746829680,
   "name": "automerge",
   "node_id": "MDU6TGFiZWwyNzQ2ODI5Njgw",
   "url": "https://api.github.com/repos/conda-forge/apache-airflow-providers-databricks-feedstock/labels/automerge"
  }
 ],
 "mergeable": null,
 "mergeable_state": "unknown",
 "merged": true,
 "merged_at": "2024-06-27T12:45:43Z",
 "number": 36,
 "state": "closed",
 "updated_at": "2024-06-27T12:45:49Z"
}