{
 "ETag": "W/\"f4ef757ca97d2f5c90edf8d9b57eeb3306ebea69df1152799378424e1571cf2c\"",
 "Last-Modified": "Tue, 25 Jun 2024 15:33:20 GMT",
 "base": {
  "repo": {
   "name": "pycrdt-feedstock"
  }
 },
 "closed_at": "2024-06-25T15:33:20Z",
 "created_at": "2024-06-25T13:51:18Z",
 "draft": false,
 "head": {
  "ref": "this_is_not_a_branch"
 },
 "html_url": "https://github.com/conda-forge/pycrdt-feedstock/pull/38",
 "id": 1937810731,
 "labels": [],
 "mergeable": null,
 "mergeable_state": "unknown",
 "merged": true,
 "merged_at": "2024-06-25T15:33:19Z",
 "number": 38,
 "state": "closed",
 "updated_at": "2024-06-25T15:33:20Z"
}