{
 "ETag": "W/\"b3af45581170e2ec4d8ff2bb4c4b7682d621ca6eb33a75912b9ce5117c27c989\"",
 "Last-Modified": "Tue, 28 May 2024 10:13:53 GMT",
 "base": {
  "repo": {
   "name": "orange3-feedstock"
  }
 },
 "closed_at": "2024-05-28T10:32:40Z",
 "created_at": "2024-02-24T14:54:01Z",
 "draft": false,
 "head": {
  "ref": "rebuild-python312-0-1_h005441"
 },
 "html_url": "https://github.com/conda-forge/orange3-feedstock/pull/133",
 "id": 1741841938,
 "labels": [
  {
   "color": "191970",
   "default": false,
   "description": "Instruct the bot to retry the PR",
   "id": 1167109987,
   "name": "bot-rerun",
   "node_id": "MDU6TGFiZWwxMTY3MTA5OTg3",
   "url": "https://api.github.com/repos/conda-forge/orange3-feedstock/labels/bot-rerun"
  }
 ],
 "mergeable": false,
 "mergeable_state": "dirty",
 "merged": false,
 "merged_at": null,
 "number": 133,
 "state": "closed",
 "updated_at": "2024-05-28T10:32:41Z"
}