{
 "ETag": "W/\"84d84eb9bf7f3b02c863d28d482e1a4138b80f1704645659e16b77f842bcfbcf\"",
 "Last-Modified": "Tue, 02 Jul 2024 04:50:04 GMT",
 "base": {
  "repo": {
   "name": "gpy-feedstock"
  }
 },
 "closed_at": null,
 "created_at": "2024-07-01T11:02:41Z",
 "draft": false,
 "head": {
  "ref": "rebuild-numpy2-0-1_hc1e22b"
 },
 "html_url": "https://github.com/conda-forge/gpy-feedstock/pull/41",
 "id": 1947063787,
 "labels": [],
 "mergeable": false,
 "mergeable_state": "dirty",
 "merged": false,
 "merged_at": null,
 "number": 41,
 "state": "open",
 "updated_at": "2024-07-02T04:50:04Z"
}