{
 "ETag": "W/\"846bf7ef21a64b5a0d7125290b37dc09a0ab1065f4a3e887da9265f73d1df600\"",
 "Last-Modified": "Tue, 28 May 2024 21:39:15 GMT",
 "base": {
  "repo": {
   "name": "python-blosc2-feedstock"
  }
 },
 "closed_at": "2024-08-18T19:36:39Z",
 "created_at": "2024-05-28T21:39:07Z",
 "draft": false,
 "head": {
  "ref": "rebuild-numpy2-0-1_h0057fa"
 },
 "html_url": "https://github.com/conda-forge/python-blosc2-feedstock/pull/12",
 "id": 1892694510,
 "labels": [
  {
   "name": "bot-rerun"
  }
 ],
 "mergeable": false,
 "mergeable_state": "dirty",
 "merged": false,
 "merged_at": null,
 "number": 12,
 "state": "closed",
 "updated_at": "2024-08-18T19:36:40Z"
}