{
 "base": {
  "repo": {
   "name": "conda-forge-pinning-feedstock"
  }
 },
 "closed_at": null,
 "created_at": "2024-07-25T20:30:00Z",
 "draft": false,
 "head": {
  "ref": "new_pin-azure_storage_queues_cpp-12.3.0-0-_h3ec9a8"
 },
 "html_url": "https://github.com/conda-forge/conda-forge-pinning-feedstock/pull/6209",
 "id": 1988302225,
 "labels": [],
 "mergeable": null,
 "mergeable_state": "unknown",
 "merged": false,
 "merged_at": null,
 "number": 6209,
 "state": "open",
 "updated_at": "2024-07-25T20:30:00Z"
}