{
 "ETag": "W/\"3bbfbadf6f40049c9e885c47bcb86741e65a35239991c209f0193b91c22d3c90\"",
 "Last-Modified": "Fri, 20 Oct 2023 19:44:28 GMT",
 "base": {
  "repo": {
   "name": "bvpy-feedstock"
  }
 },
 "closed_at": null,
 "created_at": "2023-10-20T19:44:22Z",
 "draft": false,
 "head": {
  "ref": "rebuild-python312-0-1_h670a3c"
 },
 "html_url": "https://github.com/conda-forge/bvpy-feedstock/pull/5",
 "id": 1567263928,
 "labels": [],
 "mergeable": true,
 "mergeable_state": "unstable",
 "merged": false,
 "merged_at": null,
 "number": 5,
 "state": "open",
 "updated_at": "2023-10-20T19:44:28Z"
}