{
 "ETag": "W/\"f0ea6a7e1735f485ed9e138c4f5d03e5a5ec2318fe7919e25bcdec383f337eb9\"",
 "Last-Modified": "Sun, 23 Jun 2024 19:28:18 GMT",
 "base": {
  "repo": {
   "name": "camb-feedstock"
  }
 },
 "closed_at": null,
 "created_at": "2024-06-20T10:10:45Z",
 "draft": false,
 "head": {
  "ref": "1.5.5_h732631"
 },
 "html_url": "https://github.com/conda-forge/camb-feedstock/pull/56",
 "id": 1930274006,
 "labels": [],
 "mergeable": true,
 "mergeable_state": "unstable",
 "merged": false,
 "merged_at": null,
 "number": 56,
 "state": "open",
 "updated_at": "2024-06-23T19:28:32Z"
}