{
 "ETag": "W/\"f7ad0c4b2a9425037a5f2c0172acf8166f6af74ab57e8f22c4c75e07279330cf\"",
 "Last-Modified": "Mon, 06 May 2024 23:01:03 GMT",
 "base": {
  "repo": {
   "name": "eth-utils-feedstock"
  }
 },
 "closed_at": null,
 "created_at": "2024-05-06T23:00:55Z",
 "draft": false,
 "head": {
  "ref": "4.1.1_h3de150"
 },
 "html_url": "https://github.com/conda-forge/eth-utils-feedstock/pull/36",
 "id": 1857112634,
 "labels": [],
 "mergeable": null,
 "mergeable_state": "unknown",
 "merged": false,
 "merged_at": null,
 "number": 36,
 "state": "open",
 "updated_at": "2024-05-06T23:01:03Z"
}