{
 "ETag": "W/\"2d6f83605a2050643145ab4afd3ca1be1d44a237050620009ab8ea101fdb0137\"",
 "Last-Modified": "Wed, 07 Aug 2024 02:54:08 GMT",
 "base": {
  "repo": {
   "name": "phono3py-feedstock"
  }
 },
 "closed_at": "2024-08-07T02:54:08Z",
 "created_at": "2024-08-07T02:26:51Z",
 "draft": false,
 "head": {
  "ref": "this_is_not_a_branch"
 },
 "html_url": "https://github.com/conda-forge/phono3py-feedstock/pull/79",
 "id": 2007163512,
 "labels": [],
 "mergeable": null,
 "mergeable_state": "unknown",
 "merged": true,
 "merged_at": "2024-08-07T02:54:07Z",
 "number": 79,
 "state": "closed",
 "updated_at": "2024-08-07T02:54:08Z"
}