{
 "ETag": "W/\"2e04db2c63378c981557738888c6466f739ddc54a274c36bbb1f6108e110ed33\"",
 "Last-Modified": "Wed, 31 Jul 2024 15:07:08 GMT",
 "base": {
  "repo": {
   "name": "pdm-feedstock"
  }
 },
 "closed_at": "2024-07-31T15:07:04Z",
 "created_at": "2024-07-31T15:02:18Z",
 "draft": false,
 "head": {
  "ref": "this_is_not_a_branch"
 },
 "html_url": "https://github.com/conda-forge/pdm-feedstock/pull/121",
 "id": 1996617379,
 "labels": [],
 "mergeable": null,
 "mergeable_state": "unknown",
 "merged": true,
 "merged_at": "2024-07-31T15:07:04Z",
 "number": 121,
 "state": "closed",
 "updated_at": "2024-07-31T15:07:08Z"
}