{
 "ETag": "W/\"de491140676847b1fd1c03c918a10460981ad9e18ae583f985a0d6461a6d9814\"",
 "Last-Modified": "Mon, 03 Jun 2024 14:59:39 GMT",
 "base": {
  "repo": {
   "name": "ipyslides-feedstock"
  }
 },
 "closed_at": "2024-06-03T14:59:38Z",
 "created_at": "2024-06-02T23:22:50Z",
 "draft": false,
 "head": {
  "ref": "this_is_not_a_branch"
 },
 "html_url": "https://github.com/conda-forge/ipyslides-feedstock/pull/143",
 "id": 1899750804,
 "labels": [],
 "mergeable": null,
 "mergeable_state": "unknown",
 "merged": true,
 "merged_at": "2024-06-03T14:59:38Z",
 "number": 143,
 "state": "closed",
 "updated_at": "2024-06-03T14:59:39Z"
}