{
 "ETag": "W/\"571ed0bdeb6e62d775b7eeaf4f869cb6f9fc4192bd19d17133581033bd8cced4\"",
 "Last-Modified": "Tue, 06 Aug 2024 14:26:46 GMT",
 "base": {
  "repo": {
   "name": "r-lokern-feedstock"
  }
 },
 "closed_at": null,
 "created_at": "2024-07-30T13:32:00Z",
 "draft": false,
 "head": {
  "ref": "1.1_12_h57de0e"
 },
 "html_url": "https://github.com/conda-forge/r-lokern-feedstock/pull/21",
 "id": 1994441297,
 "labels": [],
 "mergeable": true,
 "mergeable_state": "unstable",
 "merged": false,
 "merged_at": null,
 "number": 21,
 "state": "open",
 "updated_at": "2024-08-06T14:26:46Z"
}