{
 "ETag": "W/\"29a48e877d3f7093e66548e8cfb81b8dac8e0c8ab752d3a33414266e01dc8204\"",
 "Last-Modified": "Sun, 09 Jun 2024 10:07:18 GMT",
 "base": {
  "repo": {
   "name": "filepattern-feedstock"
  }
 },
 "closed_at": null,
 "created_at": "2024-06-09T06:22:17Z",
 "draft": false,
 "head": {
  "ref": "2.0.7_hd689ed"
 },
 "html_url": "https://github.com/conda-forge/filepattern-feedstock/pull/7",
 "id": 1910596062,
 "labels": [
  {
   "color": "191970",
   "default": false,
   "description": "Instruct the bot to retry the PR",
   "id": 6258927091,
   "name": "bot-rerun",
   "node_id": "LA_kwDOKyu0rc8AAAABdQ-l8w",
   "url": "https://api.github.com/repos/conda-forge/filepattern-feedstock/labels/bot-rerun"
  }
 ],
 "mergeable": true,
 "mergeable_state": "unstable",
 "merged": false,
 "merged_at": null,
 "number": 7,
 "state": "open",
 "updated_at": "2024-06-09T10:07:18Z"
}