{
 "ETag": "W/\"61a7318513ff3663e70785eab70307bdc4050268cf109101f4f4291405ce7f51\"",
 "Last-Modified": "Fri, 03 May 2024 00:58:20 GMT",
 "base": {
  "repo": {
   "name": "cudadecon-feedstock"
  }
 },
 "closed_at": null,
 "created_at": "2023-11-16T23:05:02Z",
 "draft": true,
 "head": {
  "ref": "rebuild-cuda120-0-3_habf50c"
 },
 "html_url": "https://github.com/conda-forge/cudadecon-feedstock/pull/27",
 "id": 1605383219,
 "labels": [],
 "mergeable": false,
 "mergeable_state": "dirty",
 "merged": false,
 "merged_at": null,
 "number": 27,
 "state": "open",
 "updated_at": "2024-05-03T00:58:20Z"
}