{
 "ETag": "W/\"2ee59eb508cc263a95836cb468490bd04a4f46f13e7ac9c983aa92cf9194a4e0\"",
 "Last-Modified": "Sun, 17 Mar 2024 05:49:45 GMT",
 "base": {
  "repo": {
   "name": "hera-workflows-feedstock"
  }
 },
 "closed_at": null,
 "created_at": "2024-03-17T05:49:38Z",
 "draft": false,
 "head": {
  "ref": "5.14.3_h0945cf"
 },
 "html_url": "https://github.com/conda-forge/hera-workflows-feedstock/pull/53",
 "id": 1775903745,
 "labels": [],
 "mergeable": true,
 "mergeable_state": "clean",
 "merged": false,
 "merged_at": null,
 "number": 53,
 "state": "open",
 "updated_at": "2024-03-17T05:49:45Z"
}