{
 "ETag": "W/\"86dd0c8b975f63059d8ab45648f55b4d03bf2a6629b2db5acb05ac0aa434a33c\"",
 "Last-Modified": "Wed, 14 Aug 2024 08:28:25 GMT",
 "base": {
  "repo": {
   "name": "pylhc_submitter-feedstock"
  }
 },
 "closed_at": "2024-08-14T08:28:25Z",
 "created_at": "2024-08-14T04:59:32Z",
 "draft": false,
 "head": {
  "ref": "this_is_not_a_branch"
 },
 "html_url": "https://github.com/conda-forge/pylhc_submitter-feedstock/pull/11",
 "id": 2018472046,
 "labels": [],
 "mergeable": null,
 "mergeable_state": "unknown",
 "merged": true,
 "merged_at": "2024-08-14T08:28:25Z",
 "number": 11,
 "state": "closed",
 "updated_at": "2024-08-14T08:28:25Z"
}