{
 "ETag": "W/\"004a48eb244e934fbcd4b15d80df2d29d069a0fd9910ee07352dd4bd2645b50f\"",
 "Last-Modified": "Tue, 30 Jul 2024 18:09:20 GMT",
 "base": {
  "repo": {
   "name": "sphinx-notfound-page-feedstock"
  }
 },
 "closed_at": "2024-07-30T18:09:20Z",
 "created_at": "2024-07-30T17:42:52Z",
 "draft": false,
 "head": {
  "ref": "this_is_not_a_branch"
 },
 "html_url": "https://github.com/conda-forge/sphinx-notfound-page-feedstock/pull/8",
 "id": 1994894635,
 "labels": [],
 "mergeable": null,
 "mergeable_state": "unknown",
 "merged": true,
 "merged_at": "2024-07-30T18:09:20Z",
 "number": 8,
 "state": "closed",
 "updated_at": "2024-07-30T18:09:20Z"
}